MANIFEST.in
README.md
requirements.txt
setup.py
test.py
monflux/__init__.py
monflux/monitor.py
monflux/monitor_exception.py
monflux/mysql_monitor.py
monflux/nginx_monitor.py
monflux/redis_monitor.py
monflux.egg-info/PKG-INFO
monflux.egg-info/SOURCES.txt
monflux.egg-info/dependency_links.txt
monflux.egg-info/requires.txt
monflux.egg-info/top_level.txt