Metadata-Version: 1.0
Name: monflux
Version: 0.0.5
Summary: collecting and reporting redis/mysql/nginx metrics , save data to influxdb
Home-page: https://github.com/peablog/monflux
Author: peablog
Author-email: peablog@qq.com
License: MIT License
Platform: UNKNOWN
